{
  "url": "https://dxs.tw",
  "canonicalURL": "https://dxs.tw",
  "httpStatus": 200,
  "timestamp": "2026-01-06T21:00:07.038Z",
  "testParameters": {
    "customDNS": "168.95.1.1",
    "useAdblock": true,
    "adblockUrls": [
      "https://filter.futa.gg/hosts_abp.txt",
      "https://raw.githubusercontent.com/AdguardTeam/FiltersRegistry/master/filters/filter_15_DnsFilter/filter.txt"
    ],
    "useCache": true,
    "hasIPinfoToken": true
  },
  "testingEnvironment": {
    "ip": "220.132.212.194",
    "hostname": "220-132-212-194.hinet-ip.hinet.net",
    "city": "Banqiao",
    "region": "Taipei",
    "country": "TW",
    "loc": "25.0143,121.4672",
    "org": "AS3462 Data Communication Business Group",
    "timezone": "Asia/Taipei",
    "source": "ipinfo json api (direct)",
    "dnsServer": "168.95.1.1"
  },
  "requestCount": 18,
  "uniqueDomains": 2,
  "test_results": {
    "domestic": {
      "cloud": 0,
      "direct": 0
    },
    "foreign": {
      "cloud": 2,
      "direct": 0
    }
  },
  "domainDetails": [
    {
      "originalUrl": "https://www.dxs.tw/style/pc/css/read.css",
      "type": "link",
      "ipinfo": {
        "domain": "www.dxs.tw",
        "ip": "172.67.74.167",
        "city": "San Francisco",
        "region": "California",
        "country": "US",
        "loc": "37.7621,-122.3971",
        "org": "AS13335 Cloudflare, Inc.",
        "timezone": "America/Los_Angeles"
      },
      "category": "foreign/cloud"
    },
    {
      "originalUrl": "https://img.dxs.tw/8031/8031604/8031604s.jpg",
      "type": "img",
      "ipinfo": {
        "domain": "img.dxs.tw",
        "ip": "104.26.0.240",
        "city": "San Francisco",
        "region": "California",
        "country": "US",
        "loc": "37.7621,-122.3971",
        "org": "AS13335 Cloudflare, Inc.",
        "timezone": "America/Los_Angeles"
      },
      "category": "foreign/cloud"
    }
  ]
}