{
  "url": "https://gcis.nat.gov.tw",
  "canonicalURL": "https://gcis.nat.gov.tw",
  "httpStatus": 200,
  "timestamp": "2025-12-04T17:11:29.544Z",
  "testParameters": {
    "customDNS": "168.95.1.1",
    "useAdblock": true,
    "adblockUrls": [
      "https://filter.futa.gg/hosts_abp.txt",
      "https://raw.githubusercontent.com/AdguardTeam/FiltersRegistry/master/filters/filter_15_DnsFilter/filter.txt"
    ],
    "useCache": true,
    "hasIPinfoToken": true
  },
  "testingEnvironment": {
    "ip": "220.132.212.194",
    "hostname": "220-132-212-194.hinet-ip.hinet.net",
    "city": "Banqiao",
    "region": "Taipei",
    "country": "TW",
    "loc": "25.0143,121.4672",
    "org": "AS3462 Data Communication Business Group",
    "timezone": "Asia/Taipei",
    "source": "json api",
    "dnsServer": "168.95.1.1"
  },
  "requestCount": 52,
  "uniqueDomains": 4,
  "test_results": {
    "domestic": 2,
    "cloud_w_domestic_node": 1,
    "foreign": 1
  },
  "domainDetails": [
    {
      "originalUrl": "https://gcis.nat.gov.tw/mainNew/css/1130510/lsrs.css",
      "type": "link",
      "ipinfo": {
        "domain": "gcis.nat.gov.tw",
        "ip": "203.66.32.141",
        "hostname": "203-66-32-141.hinet-ip.hinet.net",
        "city": "Banqiao",
        "region": "Taipei",
        "country": "TW",
        "loc": "25.0143,121.4672",
        "org": "AS3462 Data Communication Business Group",
        "timezone": "Asia/Taipei"
      },
      "score": "O"
    },
    {
      "originalUrl": "https://www.googletagmanager.com/gtag/js?id=G-DEE1C56K4B",
      "type": "script",
      "ipinfo": {
        "domain": "www.googletagmanager.com",
        "ip": "142.250.198.72",
        "hostname": "lctsaa-ab-in-f8.1e100.net",
        "city": "Banqiao",
        "region": "Taipei",
        "country": "TW",
        "loc": "25.0143,121.4672",
        "org": "AS15169 Google LLC",
        "timezone": "Asia/Taipei"
      },
      "score": "O"
    },
    {
      "originalUrl": "https://static.addtoany.com/menu/page.js",
      "type": "script",
      "ipinfo": {
        "domain": "static.addtoany.com",
        "ip": "104.20.20.192",
        "city": "San Francisco",
        "region": "California",
        "country": "US",
        "loc": "37.7621,-122.3971",
        "org": "AS13335 Cloudflare, Inc.",
        "timezone": "America/Los_Angeles"
      },
      "score": "?"
    },
    {
      "originalUrl": "https://cdn.jsdelivr.net/npm/bootstrap-icons@1.11.1/font/bootstrap-icons.css",
      "type": "css",
      "ipinfo": {
        "domain": "cdn.jsdelivr.net",
        "ip": "151.101.1.229",
        "city": "San Francisco",
        "region": "California",
        "country": "US",
        "loc": "37.7621,-122.3971",
        "org": "AS54113 Fastly, Inc.",
        "timezone": "America/Los_Angeles"
      },
      "score": "X"
    }
  ]
}