{
  "url": "https://health.tvbs.com.tw",
  "canonicalURL": "https://health.tvbs.com.tw/",
  "httpStatus": 200,
  "timestamp": "2026-01-14T01:53:55.907Z",
  "testParameters": {
    "customDNS": "168.95.1.1",
    "useAdblock": true,
    "adblockUrls": [
      "https://raw.githubusercontent.com/AdguardTeam/FiltersRegistry/master/filters/filter_15_DnsFilter/filter.txt"
    ],
    "useCache": true,
    "hasIPinfoToken": true
  },
  "testingEnvironment": {
    "ip": "220.132.212.194",
    "hostname": "220-132-212-194.hinet-ip.hinet.net",
    "city": "Banqiao",
    "region": "Taipei",
    "country": "TW",
    "loc": "25.0143,121.4672",
    "org": "AS3462 Data Communication Business Group",
    "timezone": "Asia/Taipei",
    "source": "ipinfo json api (direct)",
    "dnsServer": "168.95.1.1"
  },
  "requestCount": 148,
  "uniqueDomains": 4,
  "test_results": {
    "domestic": {
      "cloud": 4,
      "direct": 0
    },
    "foreign": {
      "cloud": 0,
      "direct": 0
    }
  },
  "domainDetails": [
    {
      "originalUrl": "https://health.tvbs.com.tw/",
      "type": "document",
      "ipinfo": {
        "domain": "health.tvbs.com.tw",
        "ip": "203.69.138.217",
        "hostname": "203-69-138-217.hinet-ip.hinet.net",
        "city": "Banqiao",
        "region": "Taipei",
        "country": "TW",
        "loc": "25.0143,121.4672",
        "org": "AS20940 Akamai International B.V.",
        "timezone": "Asia/Taipei"
      },
      "category": "domestic/cloud"
    },
    {
      "originalUrl": "https://static.tvbs.com.tw/health2.0/images/uploads/2026/01/20260106160051-u3Hk21QO.webp",
      "type": "image",
      "ipinfo": {
        "domain": "static.tvbs.com.tw",
        "ip": "203.69.138.215",
        "hostname": "203-69-138-215.hinet-ip.hinet.net",
        "city": "Banqiao",
        "region": "Taipei",
        "country": "TW",
        "loc": "25.0143,121.4672",
        "org": "AS20940 Akamai International B.V.",
        "timezone": "Asia/Taipei"
      },
      "category": "domestic/cloud"
    },
    {
      "originalUrl": "https://cc.tvbs.com.tw/img/program/upload/health/health_body/20221122110829_637c3d2d28d76_xs.svg",
      "type": "image",
      "ipinfo": {
        "domain": "cc.tvbs.com.tw",
        "ip": "203.69.138.233",
        "hostname": "203-69-138-233.hinet-ip.hinet.net",
        "city": "Banqiao",
        "region": "Taipei",
        "country": "TW",
        "loc": "25.0143,121.4672",
        "org": "AS20940 Akamai International B.V.",
        "timezone": "Asia/Taipei"
      },
      "category": "domestic/cloud"
    },
    {
      "originalUrl": "https://www.googletagmanager.com/gtm.js?id=GTM-KPDJH4D",
      "type": "script",
      "ipinfo": {
        "domain": "www.googletagmanager.com",
        "ip": "142.250.204.40",
        "hostname": "hkg07s38-in-f8.1e100.net",
        "city": "Banqiao",
        "region": "Taipei",
        "country": "TW",
        "loc": "25.0143,121.4672",
        "org": "AS15169 Google LLC",
        "timezone": "Asia/Taipei"
      },
      "category": "domestic/cloud"
    }
  ]
}