{
  "url": "https://post.gov.tw",
  "canonicalURL": "https://post.gov.tw",
  "httpStatus": null,
  "timestamp": "2026-07-20T19:13:12.816Z",
  "testParameters": {
    "customDNS": "168.95.1.1",
    "useAdblock": true,
    "adblockUrls": [
      "https://filter.futa.gg/hosts_abp.txt",
      "https://raw.githubusercontent.com/AdguardTeam/FiltersRegistry/master/filters/filter_15_DnsFilter/filter.txt"
    ],
    "useCache": true,
    "hasIPinfoToken": true
  },
  "testingEnvironment": null,
  "requestCount": 0,
  "uniqueDomains": 0,
  "testError": true,
  "errorReason": "Playwright launch failed: browserType.launch: Target page, context or browser has been closed",
  "errorDetails": {
    "message": "browserType.launch: Target page, context or browser has been closed\nBrowser logs:\n\n<launching> /Users/Irvin/Library/Caches/ms-playwright/chromium-1200/chrome-mac-arm64/Google Chrome for Testing.app/Contents/MacOS/Google Chrome for Testing --disable-field-trial-config --disable-background-networking --disable-background-timer-throttling --disable-backgrounding-occluded-windows --disable-back-forward-cache --disable-breakpad --disable-client-side-phishing-detection --disable-component-extensions-with-background-pages --disable-component-update --no-default-browser-check --disable-default-apps --disable-dev-shm-usage --disable-extensions --disable-features=AcceptCHFrame,AvoidUnnecessaryBeforeUnloadCheckSync,DestroyProfileOnBrowserClose,DialMediaRouteProvider,GlobalMediaControls,HttpsUpgrades,LensOverlay,MediaRouter,PaintHolding,ThirdPartyStoragePartitioning,Translate,AutoDeElevate,RenderDocument,OptimizationHints --enable-features=CDPScreenshotNewSurface --allow-pre-commit-input --disable-hang-monitor --disable-ipc-flooding-protection --disable-popup-blocking --disable-prompt-on-repost --disable-renderer-backgrounding --force-color-profile=srgb --metrics-recording-only --no-first-run --password-store=basic --use-mock-keychain --no-service-autorun --export-tagged-pdf --disable-search-engine-choice-screen --unsafely-disable-devtools-self-xss-warnings --edge-skip-compat-layer-relaunch --enable-automation --disable-infobars --disable-search-engine-choice-screen --disable-sync --enable-unsafe-swiftshader --no-sandbox --dns-server=168.95.1.1 --user-data-dir=/var/folders/v1/95m473f92m739yg0pp_2gxy80000gp/T/playwright_chromiumdev_profile-Bo24Ye --remote-debugging-pipe --no-startup-window\n<launched> pid=28053\n[pid=28053] <gracefully close start>\n[pid=28053][err] [28053:1359036:0721/031312.708014:ERROR:net/cert/internal/trust_store_mac.cc:807] Error parsing certificate:\n[pid=28053][err] ERROR: The policy qualifiers SEQUENCE is empty\n[pid=28053][err] ERROR: Failed parsing policy qualifiers\n[pid=28053][err] ERROR: Failed parsing certificate policies\n[pid=28053][err] \nCall log:\n  - <launching> /Users/Irvin/Library/Caches/ms-playwright/chromium-1200/chrome-mac-arm64/Google Chrome for Testing.app/Contents/MacOS/Google Chrome for Testing --disable-field-trial-config --disable-background-networking --disable-background-timer-throttling --disable-backgrounding-occluded-windows --disable-back-forward-cache --disable-breakpad --disable-client-side-phishing-detection --disable-component-extensions-with-background-pages --disable-component-update --no-default-browser-check --disable-default-apps --disable-dev-shm-usage --disable-extensions --disable-features=AcceptCHFrame,AvoidUnnecessaryBeforeUnloadCheckSync,DestroyProfileOnBrowserClose,DialMediaRouteProvider,GlobalMediaControls,HttpsUpgrades,LensOverlay,MediaRouter,PaintHolding,ThirdPartyStoragePartitioning,Translate,AutoDeElevate,RenderDocument,OptimizationHints --enable-features=CDPScreenshotNewSurface --allow-pre-commit-input --disable-hang-monitor --disable-ipc-flooding-protection --disable-popup-blocking --disable-prompt-on-repost --disable-renderer-backgrounding --force-color-profile=srgb --metrics-recording-only --no-first-run --password-store=basic --use-mock-keychain --no-service-autorun --export-tagged-pdf --disable-search-engine-choice-screen --unsafely-disable-devtools-self-xss-warnings --edge-skip-compat-layer-relaunch --enable-automation --disable-infobars --disable-search-engine-choice-screen --disable-sync --enable-unsafe-swiftshader --no-sandbox --dns-server=168.95.1.1 --user-data-dir=/var/folders/v1/95m473f92m739yg0pp_2gxy80000gp/T/playwright_chromiumdev_profile-Bo24Ye --remote-debugging-pipe --no-startup-window\n  - <launched> pid=28053\n  - [pid=28053] <gracefully close start>\n  - [pid=28053][err] [28053:1359036:0721/031312.708014:ERROR:net/cert/internal/trust_store_mac.cc:807] Error parsing certificate:\n  - [pid=28053][err] ERROR: The policy qualifiers SEQUENCE is empty\n  - [pid=28053][err] ERROR: Failed parsing policy qualifiers\n  - [pid=28053][err] ERROR: Failed parsing certificate policies\n  - [pid=28053][err]\n  - [pid=28053] <forcefully close>\n  - [pid=28053] <kill>\n  - [pid=28053] <will force kill>\n  - [pid=28053] <process did exit: exitCode=null, signal=SIGKILL>\n  - [pid=28053] starting temporary directories cleanup\n  - [pid=28053] finished temporary directories cleanup\n  - [pid=28053] <gracefully close end>\n",
    "statusCode": null
  }
}